flask_apidoc_extend/__init__.py
flask_apidoc_extend/apidoc.py
flask_apidoc_extend/utils.py
flask_apidoc_extend/templates/parse.md
flask_apidoc_extend/templates/template.md
Flask_Apidoc_Extend-0.1.8.dist-info/LICENSE
Flask_Apidoc_Extend-0.1.8.dist-info/METADATA
Flask_Apidoc_Extend-0.1.8.dist-info/WHEEL
Flask_Apidoc_Extend-0.1.8.dist-info/top_level.txt
Flask_Apidoc_Extend-0.1.8.dist-info/RECORD
