Metadata-Version: 2.1
Name: Flask-Apidoc-Extend
Version: 0.1.8
Summary: Add ApiDoc support to Flask
Home-page: https://github.com/sunyuanxiang/flask-apidoc-extend
Author: sun yuanxiang
Author-email: apidocer@163.com
License: MIT
Keywords: flask,apidoc,doc,documentation,restful,markdown
Platform: UNKNOWN
Classifier: Development Status :: 5 - Production/Stable
Classifier: Intended Audience :: Developers
Classifier: Operating System :: OS Independent
Classifier: Programming Language :: Python :: 3
Classifier: Programming Language :: Python :: Implementation :: CPython
Requires-Python: >=3.5
Requires-Dist: flask (>=0.11)
